offensivetext/__init__.py
offensivetext/text_classify.py
offensivetext/train.py
offensivetext/models/bayesian_cyberbullying_filter.sav
offensivetext/models/bayesian_racism_filter.sav
offensivetext/models/bayesian_sexism_filter.sav
offensivetext/models/bayesian_sexual_content_filter.sav
offensivetext/models/decision_cyberbullying_filter.sav
offensivetext/models/decision_racism_filter.sav
offensivetext/models/decision_sexism_filter.sav
offensivetext/models/decision_sexual_content_filter.sav
offensivetext/models/vectorizer_bayesian_cyberbullying_filter.sav
offensivetext/models/vectorizer_bayesian_racism_filter.sav
offensivetext/models/vectorizer_bayesian_sexism_filter.sav
offensivetext/models/vectorizer_bayesian_sexual_content_filter.sav
offensivetext/models/vectorizer_decision_cyberbullying_filter.sav
offensivetext/models/vectorizer_decision_racism_filter.sav
offensivetext/models/vectorizer_decision_sexism_filter.sav
offensivetext/models/vectorizer_decision_sexual_content_filter.sav
offensivetext-1.3.9.dist-info/METADATA
offensivetext-1.3.9.dist-info/WHEEL
offensivetext-1.3.9.dist-info/top_level.txt
offensivetext-1.3.9.dist-info/RECORD
